[
    {
        "fk_producto": "50",
        "0": "50",
        "fk_ingrediente": "6",
        "1": "6",
        "fk_grupo": "1",
        "2": "1",
        "cantidad": "50.00",
        "3": "50.00",
        "editable": "2",
        "4": "2",
        "activo_defecto": "1",
        "5": "1",
        "sumar": "0",
        "6": "0",
        "adicional": "0",
        "7": "0"
    },
    {
        "fk_producto": "57",
        "0": "57",
        "fk_ingrediente": "6",
        "1": "6",
        "fk_grupo": "1",
        "2": "1",
        "cantidad": "200.00",
        "3": "200.00",
        "editable": "1",
        "4": "1",
        "activo_defecto": "0",
        "5": "0",
        "sumar": "0",
        "6": "0",
        "adicional": "0",
        "7": "0"
    },
    {
        "fk_producto": "105",
        "0": "105",
        "fk_ingrediente": "6",
        "1": "6",
        "fk_grupo": "13",
        "2": "13",
        "cantidad": "5.00",
        "3": "5.00",
        "editable": "1",
        "4": "1",
        "activo_defecto": "0",
        "5": "0",
        "sumar": "1",
        "6": "1",
        "adicional": "1500",
        "7": "1500"
    },
    {
        "fk_producto": "111",
        "0": "111",
        "fk_ingrediente": "6",
        "1": "6",
        "fk_grupo": "13",
        "2": "13",
        "cantidad": "5.00",
        "3": "5.00",
        "editable": "1",
        "4": "1",
        "activo_defecto": "0",
        "5": "0",
        "sumar": "0",
        "6": "0",
        "adicional": "1000",
        "7": "1000"
    },
    {
        "fk_producto": "60",
        "0": "60",
        "fk_ingrediente": "9",
        "1": "9",
        "fk_grupo": "1",
        "2": "1",
        "cantidad": "200.00",
        "3": "200.00",
        "editable": "2",
        "4": "2",
        "activo_defecto": "1",
        "5": "1",
        "sumar": null,
        "6": null,
        "adicional": "0",
        "7": "0"
    },
    {
        "fk_producto": "8",
        "0": "8",
        "fk_ingrediente": "10",
        "1": "10",
        "fk_grupo": "10",
        "2": "10",
        "cantidad": "1.00",
        "3": "1.00",
        "editable": "1",
        "4": "1",
        "activo_defecto": "0",
        "5": "0",
        "sumar": "1",
        "6": "1",
        "adicional": "1500",
        "7": "1500"
    },
    {
        "fk_producto": "50",
        "0": "50",
        "fk_ingrediente": "10",
        "1": "10",
        "fk_grupo": "1",
        "2": "1",
        "cantidad": "2.00",
        "3": "2.00",
        "editable": "2",
        "4": "2",
        "activo_defecto": "1",
        "5": "1",
        "sumar": "0",
        "6": "0",
        "adicional": "0",
        "7": "0"
    },
    {
        "fk_producto": "104",
        "0": "104",
        "fk_ingrediente": "10",
        "1": "10",
        "fk_grupo": "10",
        "2": "10",
        "cantidad": "1.00",
        "3": "1.00",
        "editable": "1",
        "4": "1",
        "activo_defecto": "0",
        "5": "0",
        "sumar": "1",
        "6": "1",
        "adicional": "0",
        "7": "0"
    },
    {
        "fk_producto": "38",
        "0": "38",
        "fk_ingrediente": "11",
        "1": "11",
        "fk_grupo": "1",
        "2": "1",
        "cantidad": "15.00",
        "3": "15.00",
        "editable": "2",
        "4": "2",
        "activo_defecto": "1",
        "5": "1",
        "sumar": null,
        "6": null,
        "adicional": "0",
        "7": "0"
    },
    {
        "fk_producto": "1",
        "0": "1",
        "fk_ingrediente": "13",
        "1": "13",
        "fk_grupo": "9",
        "2": "9",
        "cantidad": "20.00",
        "3": "20.00",
        "editable": "1",
        "4": "1",
        "activo_defecto": "0",
        "5": "0",
        "sumar": "0",
        "6": "0",
        "adicional": "1000",
        "7": "1000"
    },
    {
        "fk_producto": "105",
        "0": "105",
        "fk_ingrediente": "13",
        "1": "13",
        "fk_grupo": "9",
        "2": "9",
        "cantidad": "20.00",
        "3": "20.00",
        "editable": "1",
        "4": "1",
        "activo_defecto": "0",
        "5": "0",
        "sumar": "1",
        "6": "1",
        "adicional": "0",
        "7": "0"
    },
    {
        "fk_producto": "111",
        "0": "111",
        "fk_ingrediente": "13",
        "1": "13",
        "fk_grupo": "9",
        "2": "9",
        "cantidad": "10.00",
        "3": "10.00",
        "editable": "1",
        "4": "1",
        "activo_defecto": "0",
        "5": "0",
        "sumar": "0",
        "6": "0",
        "adicional": "500",
        "7": "500"
    },
    {
        "fk_producto": "105",
        "0": "105",
        "fk_ingrediente": "32",
        "1": "32",
        "fk_grupo": "13",
        "2": "13",
        "cantidad": "5.00",
        "3": "5.00",
        "editable": "1",
        "4": "1",
        "activo_defecto": "0",
        "5": "0",
        "sumar": "1",
        "6": "1",
        "adicional": "1000",
        "7": "1000"
    },
    {
        "fk_producto": "111",
        "0": "111",
        "fk_ingrediente": "32",
        "1": "32",
        "fk_grupo": "13",
        "2": "13",
        "cantidad": "5.00",
        "3": "5.00",
        "editable": "1",
        "4": "1",
        "activo_defecto": "0",
        "5": "0",
        "sumar": "0",
        "6": "0",
        "adicional": "1200",
        "7": "1200"
    },
    {
        "fk_producto": "57",
        "0": "57",
        "fk_ingrediente": "54",
        "1": "54",
        "fk_grupo": "1",
        "2": "1",
        "cantidad": "200.00",
        "3": "200.00",
        "editable": "1",
        "4": "1",
        "activo_defecto": "0",
        "5": "0",
        "sumar": "1",
        "6": "1",
        "adicional": "200",
        "7": "200"
    },
    {
        "fk_producto": "60",
        "0": "60",
        "fk_ingrediente": "61",
        "1": "61",
        "fk_grupo": "1",
        "2": "1",
        "cantidad": "1.00",
        "3": "1.00",
        "editable": "2",
        "4": "2",
        "activo_defecto": "1",
        "5": "1",
        "sumar": null,
        "6": null,
        "adicional": "0",
        "7": "0"
    },
    {
        "fk_producto": "69",
        "0": "69",
        "fk_ingrediente": "70",
        "1": "70",
        "fk_grupo": "3",
        "2": "3",
        "cantidad": "1.00",
        "3": "1.00",
        "editable": "1",
        "4": "1",
        "activo_defecto": "1",
        "5": "1",
        "sumar": "1",
        "6": "1",
        "adicional": "0",
        "7": "0"
    },
    {
        "fk_producto": "69",
        "0": "69",
        "fk_ingrediente": "71",
        "1": "71",
        "fk_grupo": "3",
        "2": "3",
        "cantidad": "1.00",
        "3": "1.00",
        "editable": "1",
        "4": "1",
        "activo_defecto": "1",
        "5": "1",
        "sumar": "1",
        "6": "1",
        "adicional": "0",
        "7": "0"
    },
    {
        "fk_producto": "69",
        "0": "69",
        "fk_ingrediente": "72",
        "1": "72",
        "fk_grupo": "3",
        "2": "3",
        "cantidad": "1.00",
        "3": "1.00",
        "editable": "1",
        "4": "1",
        "activo_defecto": "1",
        "5": "1",
        "sumar": "1",
        "6": "1",
        "adicional": "0",
        "7": "0"
    },
    {
        "fk_producto": "1",
        "0": "1",
        "fk_ingrediente": "73",
        "1": "73",
        "fk_grupo": "9",
        "2": "9",
        "cantidad": "10.00",
        "3": "10.00",
        "editable": "1",
        "4": "1",
        "activo_defecto": "0",
        "5": "0",
        "sumar": "0",
        "6": "0",
        "adicional": "2000",
        "7": "2000"
    },
    {
        "fk_producto": "104",
        "0": "104",
        "fk_ingrediente": "73",
        "1": "73",
        "fk_grupo": "10",
        "2": "10",
        "cantidad": "20.00",
        "3": "20.00",
        "editable": "1",
        "4": "1",
        "activo_defecto": "0",
        "5": "0",
        "sumar": "1",
        "6": "1",
        "adicional": "0",
        "7": "0"
    },
    {
        "fk_producto": "105",
        "0": "105",
        "fk_ingrediente": "73",
        "1": "73",
        "fk_grupo": "9",
        "2": "9",
        "cantidad": "20.00",
        "3": "20.00",
        "editable": "1",
        "4": "1",
        "activo_defecto": "0",
        "5": "0",
        "sumar": "1",
        "6": "1",
        "adicional": "0",
        "7": "0"
    },
    {
        "fk_producto": "111",
        "0": "111",
        "fk_ingrediente": "73",
        "1": "73",
        "fk_grupo": "9",
        "2": "9",
        "cantidad": "10.00",
        "3": "10.00",
        "editable": "1",
        "4": "1",
        "activo_defecto": "0",
        "5": "0",
        "sumar": "0",
        "6": "0",
        "adicional": "900",
        "7": "900"
    },
    {
        "fk_producto": "74",
        "0": "74",
        "fk_ingrediente": "75",
        "1": "75",
        "fk_grupo": "1",
        "2": "1",
        "cantidad": "1.00",
        "3": "1.00",
        "editable": "1",
        "4": "1",
        "activo_defecto": "0",
        "5": "0",
        "sumar": "1",
        "6": "1",
        "adicional": "8000",
        "7": "8000"
    },
    {
        "fk_producto": "80",
        "0": "80",
        "fk_ingrediente": "81",
        "1": "81",
        "fk_grupo": "4",
        "2": "4",
        "cantidad": "1.00",
        "3": "1.00",
        "editable": "1",
        "4": "1",
        "activo_defecto": "0",
        "5": "0",
        "sumar": "1",
        "6": "1",
        "adicional": "3000",
        "7": "3000"
    },
    {
        "fk_producto": "80",
        "0": "80",
        "fk_ingrediente": "82",
        "1": "82",
        "fk_grupo": "4",
        "2": "4",
        "cantidad": "1.00",
        "3": "1.00",
        "editable": "1",
        "4": "1",
        "activo_defecto": "0",
        "5": "0",
        "sumar": "0",
        "6": "0",
        "adicional": "0",
        "7": "0"
    },
    {
        "fk_producto": "80",
        "0": "80",
        "fk_ingrediente": "83",
        "1": "83",
        "fk_grupo": "5",
        "2": "5",
        "cantidad": "1.00",
        "3": "1.00",
        "editable": "1",
        "4": "1",
        "activo_defecto": "0",
        "5": "0",
        "sumar": "1",
        "6": "1",
        "adicional": "0",
        "7": "0"
    },
    {
        "fk_producto": "80",
        "0": "80",
        "fk_ingrediente": "84",
        "1": "84",
        "fk_grupo": "5",
        "2": "5",
        "cantidad": "1.00",
        "3": "1.00",
        "editable": "1",
        "4": "1",
        "activo_defecto": "0",
        "5": "0",
        "sumar": "1",
        "6": "1",
        "adicional": "0",
        "7": "0"
    },
    {
        "fk_producto": "80",
        "0": "80",
        "fk_ingrediente": "85",
        "1": "85",
        "fk_grupo": "5",
        "2": "5",
        "cantidad": "1.00",
        "3": "1.00",
        "editable": "1",
        "4": "1",
        "activo_defecto": "0",
        "5": "0",
        "sumar": "1",
        "6": "1",
        "adicional": "0",
        "7": "0"
    },
    {
        "fk_producto": "80",
        "0": "80",
        "fk_ingrediente": "86",
        "1": "86",
        "fk_grupo": "5",
        "2": "5",
        "cantidad": "1.00",
        "3": "1.00",
        "editable": "1",
        "4": "1",
        "activo_defecto": "0",
        "5": "0",
        "sumar": "1",
        "6": "1",
        "adicional": "1000",
        "7": "1000"
    },
    {
        "fk_producto": "80",
        "0": "80",
        "fk_ingrediente": "87",
        "1": "87",
        "fk_grupo": "6",
        "2": "6",
        "cantidad": "1.00",
        "3": "1.00",
        "editable": "1",
        "4": "1",
        "activo_defecto": "0",
        "5": "0",
        "sumar": "1",
        "6": "1",
        "adicional": "0",
        "7": "0"
    },
    {
        "fk_producto": "80",
        "0": "80",
        "fk_ingrediente": "88",
        "1": "88",
        "fk_grupo": "6",
        "2": "6",
        "cantidad": "1.00",
        "3": "1.00",
        "editable": "1",
        "4": "1",
        "activo_defecto": "0",
        "5": "0",
        "sumar": "1",
        "6": "1",
        "adicional": "0",
        "7": "0"
    },
    {
        "fk_producto": "80",
        "0": "80",
        "fk_ingrediente": "89",
        "1": "89",
        "fk_grupo": "6",
        "2": "6",
        "cantidad": "1.00",
        "3": "1.00",
        "editable": "1",
        "4": "1",
        "activo_defecto": "0",
        "5": "0",
        "sumar": "1",
        "6": "1",
        "adicional": "1500",
        "7": "1500"
    },
    {
        "fk_producto": "80",
        "0": "80",
        "fk_ingrediente": "91",
        "1": "91",
        "fk_grupo": "7",
        "2": "7",
        "cantidad": "1.00",
        "3": "1.00",
        "editable": "1",
        "4": "1",
        "activo_defecto": "0",
        "5": "0",
        "sumar": "1",
        "6": "1",
        "adicional": "0",
        "7": "0"
    },
    {
        "fk_producto": "80",
        "0": "80",
        "fk_ingrediente": "92",
        "1": "92",
        "fk_grupo": "7",
        "2": "7",
        "cantidad": "1.00",
        "3": "1.00",
        "editable": "1",
        "4": "1",
        "activo_defecto": "0",
        "5": "0",
        "sumar": "1",
        "6": "1",
        "adicional": "0",
        "7": "0"
    },
    {
        "fk_producto": "80",
        "0": "80",
        "fk_ingrediente": "93",
        "1": "93",
        "fk_grupo": "7",
        "2": "7",
        "cantidad": "1.00",
        "3": "1.00",
        "editable": "1",
        "4": "1",
        "activo_defecto": "0",
        "5": "0",
        "sumar": "1",
        "6": "1",
        "adicional": "0",
        "7": "0"
    },
    {
        "fk_producto": "80",
        "0": "80",
        "fk_ingrediente": "94",
        "1": "94",
        "fk_grupo": "7",
        "2": "7",
        "cantidad": "1.00",
        "3": "1.00",
        "editable": "1",
        "4": "1",
        "activo_defecto": "0",
        "5": "0",
        "sumar": "1",
        "6": "1",
        "adicional": "0",
        "7": "0"
    },
    {
        "fk_producto": "1",
        "0": "1",
        "fk_ingrediente": "98",
        "1": "98",
        "fk_grupo": "9",
        "2": "9",
        "cantidad": "1.00",
        "3": "1.00",
        "editable": "1",
        "4": "1",
        "activo_defecto": "0",
        "5": "0",
        "sumar": "0",
        "6": "0",
        "adicional": "2500",
        "7": "2500"
    },
    {
        "fk_producto": "105",
        "0": "105",
        "fk_ingrediente": "98",
        "1": "98",
        "fk_grupo": "9",
        "2": "9",
        "cantidad": "1.00",
        "3": "1.00",
        "editable": "1",
        "4": "1",
        "activo_defecto": "0",
        "5": "0",
        "sumar": "1",
        "6": "1",
        "adicional": "0",
        "7": "0"
    },
    {
        "fk_producto": "111",
        "0": "111",
        "fk_ingrediente": "98",
        "1": "98",
        "fk_grupo": "9",
        "2": "9",
        "cantidad": "1.00",
        "3": "1.00",
        "editable": "1",
        "4": "1",
        "activo_defecto": "0",
        "5": "0",
        "sumar": "0",
        "6": "0",
        "adicional": "1000",
        "7": "1000"
    },
    {
        "fk_producto": "1",
        "0": "1",
        "fk_ingrediente": "100",
        "1": "100",
        "fk_grupo": "9",
        "2": "9",
        "cantidad": "1.00",
        "3": "1.00",
        "editable": "1",
        "4": "1",
        "activo_defecto": "0",
        "5": "0",
        "sumar": "0",
        "6": "0",
        "adicional": "1500",
        "7": "1500"
    },
    {
        "fk_producto": "105",
        "0": "105",
        "fk_ingrediente": "100",
        "1": "100",
        "fk_grupo": "9",
        "2": "9",
        "cantidad": "1.00",
        "3": "1.00",
        "editable": "1",
        "4": "1",
        "activo_defecto": "0",
        "5": "0",
        "sumar": "1",
        "6": "1",
        "adicional": "0",
        "7": "0"
    },
    {
        "fk_producto": "111",
        "0": "111",
        "fk_ingrediente": "100",
        "1": "100",
        "fk_grupo": "9",
        "2": "9",
        "cantidad": "1.00",
        "3": "1.00",
        "editable": "1",
        "4": "1",
        "activo_defecto": "0",
        "5": "0",
        "sumar": "0",
        "6": "0",
        "adicional": "800",
        "7": "800"
    },
    {
        "fk_producto": "1",
        "0": "1",
        "fk_ingrediente": "101",
        "1": "101",
        "fk_grupo": "9",
        "2": "9",
        "cantidad": "1.00",
        "3": "1.00",
        "editable": "1",
        "4": "1",
        "activo_defecto": "0",
        "5": "0",
        "sumar": "0",
        "6": "0",
        "adicional": "1000",
        "7": "1000"
    },
    {
        "fk_producto": "8",
        "0": "8",
        "fk_ingrediente": "103",
        "1": "103",
        "fk_grupo": "10",
        "2": "10",
        "cantidad": "1.00",
        "3": "1.00",
        "editable": "1",
        "4": "1",
        "activo_defecto": "0",
        "5": "0",
        "sumar": "1",
        "6": "1",
        "adicional": "3000",
        "7": "3000"
    },
    {
        "fk_producto": "104",
        "0": "104",
        "fk_ingrediente": "103",
        "1": "103",
        "fk_grupo": "10",
        "2": "10",
        "cantidad": "1.00",
        "3": "1.00",
        "editable": "1",
        "4": "1",
        "activo_defecto": "0",
        "5": "0",
        "sumar": "0",
        "6": "0",
        "adicional": "0",
        "7": "0"
    },
    {
        "fk_producto": "4",
        "0": "4",
        "fk_ingrediente": "106",
        "1": "106",
        "fk_grupo": "10",
        "2": "10",
        "cantidad": "1.00",
        "3": "1.00",
        "editable": "1",
        "4": "1",
        "activo_defecto": "0",
        "5": "0",
        "sumar": "1",
        "6": "1",
        "adicional": "0",
        "7": "0"
    },
    {
        "fk_producto": "4",
        "0": "4",
        "fk_ingrediente": "107",
        "1": "107",
        "fk_grupo": "10",
        "2": "10",
        "cantidad": "1.00",
        "3": "1.00",
        "editable": "1",
        "4": "1",
        "activo_defecto": "0",
        "5": "0",
        "sumar": "1",
        "6": "1",
        "adicional": "0",
        "7": "0"
    },
    {
        "fk_producto": "5",
        "0": "5",
        "fk_ingrediente": "108",
        "1": "108",
        "fk_grupo": "11",
        "2": "11",
        "cantidad": "1.00",
        "3": "1.00",
        "editable": "2",
        "4": "2",
        "activo_defecto": "1",
        "5": "1",
        "sumar": "0",
        "6": "0",
        "adicional": "0",
        "7": "0"
    },
    {
        "fk_producto": "5",
        "0": "5",
        "fk_ingrediente": "109",
        "1": "109",
        "fk_grupo": "11",
        "2": "11",
        "cantidad": "1.00",
        "3": "1.00",
        "editable": "1",
        "4": "1",
        "activo_defecto": "0",
        "5": "0",
        "sumar": "1",
        "6": "1",
        "adicional": "0",
        "7": "0"
    },
    {
        "fk_producto": "5",
        "0": "5",
        "fk_ingrediente": "110",
        "1": "110",
        "fk_grupo": "11",
        "2": "11",
        "cantidad": "1.00",
        "3": "1.00",
        "editable": "1",
        "4": "1",
        "activo_defecto": "0",
        "5": "0",
        "sumar": "0",
        "6": "0",
        "adicional": "0",
        "7": "0"
    },
    {
        "fk_producto": "105",
        "0": "105",
        "fk_ingrediente": "112",
        "1": "112",
        "fk_grupo": "12",
        "2": "12",
        "cantidad": "1.00",
        "3": "1.00",
        "editable": "1",
        "4": "1",
        "activo_defecto": "0",
        "5": "0",
        "sumar": "0",
        "6": "0",
        "adicional": "1500",
        "7": "1500"
    },
    {
        "fk_producto": "111",
        "0": "111",
        "fk_ingrediente": "112",
        "1": "112",
        "fk_grupo": "12",
        "2": "12",
        "cantidad": "1.00",
        "3": "1.00",
        "editable": "1",
        "4": "1",
        "activo_defecto": "0",
        "5": "0",
        "sumar": "1",
        "6": "1",
        "adicional": "1000",
        "7": "1000"
    },
    {
        "fk_producto": "105",
        "0": "105",
        "fk_ingrediente": "113",
        "1": "113",
        "fk_grupo": "12",
        "2": "12",
        "cantidad": "1.00",
        "3": "1.00",
        "editable": "1",
        "4": "1",
        "activo_defecto": "0",
        "5": "0",
        "sumar": "0",
        "6": "0",
        "adicional": "2000",
        "7": "2000"
    },
    {
        "fk_producto": "111",
        "0": "111",
        "fk_ingrediente": "113",
        "1": "113",
        "fk_grupo": "12",
        "2": "12",
        "cantidad": "1.00",
        "3": "1.00",
        "editable": "1",
        "4": "1",
        "activo_defecto": "0",
        "5": "0",
        "sumar": "1",
        "6": "1",
        "adicional": "1500",
        "7": "1500"
    }
]